<?xml version="1.0" encoding="utf-8"?><index><stem n="go"><phr n="go"><ent r="3" t="4" w="120" /><ent r="3" t="4" w="120" /><ent r="6" t="18" w="140" /><ent r="6" t="18" w="140" /><ent r="6" t="18" w="182" /><ent r="6" t="18" w="182" /><ent r="6" t="18" w="223" /><ent r="6" t="18" w="223" /><ent r="6" t="18" w="239" /><ent r="6" t="18" w="239" /></phr><phr n="Go"><ent r="3" t="4" w="278" /><ent r="3" t="4" w="278" /></phr><phr n="going"><ent r="3" t="29" w="424" /><ent r="3" t="29" w="424" /><ent r="4" t="61" w="359" /><ent r="4" t="61" w="359" /></phr></stem><stem n="www"><phr n="www"><ent r="64" t="4" w="124" /><ent r="64" t="4" w="153" /><ent r="67" t="5" w="233" /></phr></stem><stem n="development-partn"><phr n="development-partner"><ent r="64" t="4" w="128" /></phr></stem><stem n="development-partner-program"><phr n="development-partner-program"><ent r="64" t="4" w="128" /></phr></stem><stem n="partner-program"><phr n="partner-program"><ent r="64" t="4" w="129" /></phr></stem><stem n="knowledgebas"><phr n="Knowledgebase"><ent r="92" t="4" w="135" /><ent r="92" t="4" w="135" /><ent r="3" t="4" w="142" /><ent r="3" t="4" w="142" /><ent r="7" t="17" w="7121" /><ent r="7" t="17" w="7121" /></phr><phr n="knowledgebase"><ent r="3" t="4" w="149" /><ent r="3" t="4" w="149" /></phr></stem><stem n="faq"><phr n="FAQs"><ent r="3" t="4" w="144" /><ent r="3" t="4" w="144" /></phr></stem><stem n="articl"><phr n="articles"><ent r="3" t="4" w="150" /></phr><phr n="Articles"><ent r="7" t="17" w="7122" /><ent r="7" t="17" w="7122" /></phr></stem><stem n="interact"><phr n="interactive"><ent r="3" t="4" w="180" /><ent r="3" t="4" w="180" /></phr><phr n="interactions"><ent r="3" t="8" w="110" /><ent r="3" t="8" w="110" /></phr><phr n="interact"><ent r="4" t="19" w="193" /><ent r="4" t="19" w="193" /><ent r="4" t="20" w="154" /><ent r="4" t="20" w="154" /><ent r="4" t="21" w="120" /><ent r="4" t="21" w="120" /><ent r="4" t="22" w="80" /><ent r="4" t="22" w="80" /><ent r="3" t="25" w="33" /><ent r="3" t="25" w="33" /><ent r="3" t="59" w="42" /><ent r="3" t="59" w="42" /></phr></stem><stem n="excel"><phr n="excellent"><ent r="3" t="4" w="186" /><ent r="3" t="4" w="186" /></phr><phr n="excel"><ent r="6" t="79" w="688" /><ent r="6" t="79" w="3326" /><ent r="6" t="79" w="3326" /><ent r="6" t="79" w="3442" /><ent r="6" t="79" w="3442" /></phr></stem><stem n="discuss"><phr n="discussion"><ent r="3" t="4" w="189" /></phr><phr n="Discussion"><ent r="92" t="4" w="209" /><ent r="92" t="4" w="209" /><ent r="3" t="4" w="213" /><ent r="3" t="4" w="213" /><ent r="3" t="4" w="244" /><ent r="3" t="4" w="244" /></phr></stem><stem n="group"><phr n="Groups"><ent r="92" t="4" w="210" /><ent r="92" t="4" w="210" /><ent r="3" t="4" w="214" /><ent r="3" t="4" w="214" /><ent r="3" t="4" w="245" /><ent r="3" t="4" w="245" /><ent r="6" t="7" w="495" /><ent r="6" t="7" w="585" /><ent r="6" t="7" w="856" /><ent r="6" t="7" w="867" /><ent r="6" t="7" w="875" /><ent r="6" t="7" w="883" /><ent r="6" t="7" w="891" /><ent r="6" t="7" w="901" /><ent r="6" t="7" w="1295" /><ent r="6" t="7" w="1303" /><ent r="7" t="17" w="590" /><ent r="7" t="17" w="590" /><ent r="7" t="17" w="861" /><ent r="7" t="17" w="1214" /><ent r="7" t="17" w="1214" /><ent r="7" t="17" w="1226" /><ent r="7" t="17" w="1226" /><ent r="7" t="17" w="1722" /><ent r="7" t="17" w="1722" /><ent r="7" t="17" w="2703" /><ent r="7" t="17" w="2703" /><ent r="7" t="17" w="2715" /><ent r="7" t="17" w="2715" /><ent r="7" t="17" w="3314" /><ent r="7" t="17" w="3314" /><ent r="7" t="17" w="3326" /><ent r="7" t="17" w="3326" /><ent r="67" t="17" w="3923" /><ent r="67" t="17" w="3923" /><ent r="8" t="17" w="3933" /><ent r="8" t="17" w="3933" /><ent r="8" t="17" w="4146" /><ent r="8" t="17" w="4146" /><ent r="8" t="17" w="5061" /><ent r="8" t="17" w="5061" /><ent r="64" t="23" w="139" /><ent r="64" t="23" w="139" /><ent r="3" t="26" w="55" /><ent r="3" t="27" w="261" /><ent r="3" t="27" w="261" /><ent r="3" t="27" w="272" /><ent r="3" t="27" w="275" /><ent r="3" t="27" w="276" /><ent r="3" t="27" w="276" /><ent r="3" t="27" w="481" /><ent r="3" t="27" w="481" /><ent r="3" t="27" w="522" /><ent r="3" t="28" w="206" /><ent r="3" t="29" w="127" /><ent r="3" t="31" w="37" /><ent r="3" t="31" w="37" /><ent r="3" t="31" w="277" /><ent r="3" t="31" w="277" /><ent r="3" t="31" w="605" /><ent r="3" t="31" w="680" /><ent r="3" t="31" w="680" /><ent r="3" t="34" w="172" /><ent r="1000" t="40" w="1" /><ent r="1000" t="40" w="1" /><ent r="100" t="40" w="6" /><ent r="100" t="40" w="6" /><ent r="102" t="40" w="10" /><ent r="102" t="40" w="10" /><ent r="3" t="40" w="15" /><ent r="3" t="40" w="15" /><ent r="3" t="40" w="35" /><ent r="3" t="40" w="35" /><ent r="3" t="40" w="61" /><ent r="3" t="40" w="61" /><ent r="3" t="40" w="122" /><ent r="3" t="40" w="122" /><ent r="3" t="40" w="146" /><ent r="3" t="40" w="146" /><ent r="64" t="40" w="163" /><ent r="64" t="40" w="163" /><ent r="1000" t="41" w="1" /><ent r="1000" t="41" w="1" /><ent r="100" t="41" w="6" /><ent r="100" t="41" w="6" /><ent r="102" t="41" w="11" /><ent r="102" t="41" w="11" /><ent r="3" t="41" w="27" /><ent r="3" t="41" w="27" /><ent r="3" t="41" w="50" /><ent r="3" t="41" w="50" /><ent r="4" t="41" w="71" /><ent r="4" t="41" w="71" /><ent r="3" t="41" w="139" /><ent r="3" t="41" w="139" /><ent r="4" t="41" w="161" /><ent r="4" t="41" w="161" /><ent r="3" t="44" w="18" /><ent r="3" t="59" w="58" /><ent r="3" t="59" w="58" /><ent r="4" t="83" w="74" /><ent r="5" t="83" w="244" /></phr><phr n="groups"><ent r="6" t="7" w="491" /><ent r="6" t="7" w="491" /><ent r="6" t="7" w="581" /><ent r="6" t="7" w="581" /><ent r="6" t="7" w="849" /><ent r="6" t="7" w="859" /><ent r="6" t="7" w="870" /><ent r="6" t="7" w="878" /><ent r="6" t="7" w="886" /><ent r="6" t="7" w="894" /><ent r="6" t="7" w="1011" /><ent r="6" t="7" w="1011" /><ent r="3" t="25" w="64" /><ent r="3" t="29" w="274" /><ent r="3" t="29" w="274" /><ent r="3" t="29" w="403" /><ent r="4" t="41" w="94" /><ent r="4" t="41" w="94" /><ent r="4" t="41" w="117" /><ent r="4" t="41" w="117" /><ent r="3" t="43" w="23" /><ent r="6" t="79" w="1966" /></phr><phr n="Group"><ent r="6" t="16" w="200" /><ent r="6" t="16" w="200" /><ent r="7" t="17" w="601" /><ent r="7" t="17" w="601" /><ent r="7" t="17" w="1266" /><ent r="7" t="17" w="1266" /><ent r="66" t="17" w="1700" /><ent r="66" t="17" w="1700" /><ent r="7" t="17" w="2301" /><ent r="7" t="17" w="2301" /><ent r="7" t="17" w="2755" /><ent r="7" t="17" w="2755" /><ent r="7" t="17" w="3366" /><ent r="7" t="17" w="3366" /><ent r="7" t="17" w="3896" /><ent r="8" t="17" w="3992" /><ent r="8" t="17" w="3992" /><ent r="8" t="17" w="4005" /><ent r="8" t="17" w="4005" /><ent r="8" t="17" w="4019" /><ent r="8" t="17" w="4019" /><ent r="8" t="17" w="4059" /><ent r="8" t="17" w="4059" /><ent r="8" t="17" w="4067" /><ent r="8" t="17" w="4067" /><ent r="8" t="17" w="4108" /><ent r="8" t="17" w="4205" /><ent r="8" t="17" w="4205" /><ent r="8" t="17" w="4218" /><ent r="8" t="17" w="4218" /><ent r="8" t="17" w="4232" /><ent r="8" t="17" w="4232" /><ent r="8" t="17" w="4272" /><ent r="8" t="17" w="4272" /><ent r="8" t="17" w="4280" /><ent r="8" t="17" w="4280" /><ent r="7" t="17" w="5835" /><ent r="7" t="17" w="5835" /><ent r="7" t="17" w="5847" /><ent r="7" t="17" w="5847" /><ent r="7" t="17" w="5860" /><ent r="7" t="17" w="5860" /><ent r="7" t="17" w="5873" /><ent r="7" t="17" w="5873" /><ent r="7" t="17" w="5886" /><ent r="7" t="17" w="5886" /><ent r="7" t="17" w="5900" /><ent r="7" t="17" w="5900" /><ent r="7" t="17" w="6247" /><ent r="7" t="17" w="6247" /><ent r="3" t="27" w="791" /><ent r="3" t="34" w="265" /><ent r="3" t="56" w="118" /><ent r="3" t="56" w="118" /><ent r="3" t="56" w="175" /><ent r="4" t="58" w="109" /><ent r="5" t="59" w="134" /><ent r="4" t="64" w="82" /><ent r="4" t="64" w="83" /><ent r="4" t="64" w="83" /></phr><phr n="group"><ent r="7" t="17" w="599" /><ent r="7" t="17" w="599" /><ent r="7" t="17" w="1223" /><ent r="7" t="17" w="1223" /><ent r="7" t="17" w="1235" /><ent r="7" t="17" w="1247" /><ent r="7" t="17" w="1260" /><ent r="7" t="17" w="1289" /><ent r="7" t="17" w="1289" /><ent r="7" t="17" w="1302" /><ent r="7" t="17" w="1302" /><ent r="7" t="17" w="1316" /><ent r="7" t="17" w="1316" /><ent r="7" t="17" w="1731" /><ent r="7" t="17" w="1743" /><ent r="7" t="17" w="1756" /><ent r="7" t="17" w="2336" /><ent r="7" t="17" w="2336" /><ent r="7" t="17" w="2712" /><ent r="7" t="17" w="2712" /><ent r="7" t="17" w="2724" /><ent r="7" t="17" w="2736" /><ent r="7" t="17" w="2749" /><ent r="7" t="17" w="2778" /><ent r="7" t="17" w="2778" /><ent r="7" t="17" w="2791" /><ent r="7" t="17" w="2791" /><ent r="7" t="17" w="2805" /><ent r="7" t="17" w="2805" /><ent r="7" t="17" w="3323" /><ent r="7" t="17" w="3323" /><ent r="7" t="17" w="3335" /><ent r="7" t="17" w="3347" /><ent r="7" t="17" w="3360" /><ent r="7" t="17" w="3389" /><ent r="7" t="17" w="3389" /><ent r="7" t="17" w="3402" /><ent r="7" t="17" w="3402" /><ent r="7" t="17" w="3416" /><ent r="7" t="17" w="3416" /><ent r="7" t="17" w="3904" /><ent r="7" t="17" w="3919" /><ent r="6" t="17" w="3931" /><ent r="6" t="17" w="3931" /><ent r="8" t="17" w="3941" /><ent r="8" t="17" w="3941" /><ent r="8" t="17" w="3953" /><ent r="8" t="17" w="3965" /><ent r="8" t="17" w="3977" /><ent r="8" t="17" w="3988" /><ent r="8" t="17" w="4001" /><ent r="8" t="17" w="4014" /><ent r="8" t="17" w="4028" /><ent r="8" t="17" w="4042" /><ent r="8" t="17" w="4055" /><ent r="8" t="17" w="4082" /><ent r="8" t="17" w="4093" /><ent r="8" t="17" w="4104" /><ent r="8" t="17" w="4116" /><ent r="8" t="17" w="4130" /><ent r="8" t="17" w="4143" /><ent r="8" t="17" w="4154" /><ent r="8" t="17" w="4154" /><ent r="8" t="17" w="4166" /><ent r="8" t="17" w="4178" /><ent r="8" t="17" w="4190" /><ent r="8" t="17" w="4201" /><ent r="8" t="17" w="4214" /><ent r="8" t="17" w="4227" /><ent r="8" t="17" w="4241" /><ent r="8" t="17" w="4255" /><ent r="8" t="17" w="4268" /><ent r="8" t="17" w="4295" /><ent r="5" t="17" w="4306" /><ent r="7" t="17" w="4317" /><ent r="7" t="17" w="4330" /><ent r="7" t="17" w="4344" /><ent r="7" t="17" w="4358" /><ent r="7" t="17" w="4370" /><ent r="7" t="17" w="4438" /><ent r="7" t="17" w="4452" /><ent r="7" t="17" w="4467" /><ent r="7" t="17" w="4479" /><ent r="7" t="17" w="4491" /><ent r="7" t="17" w="4503" /><ent r="8" t="17" w="4517" /><ent r="8" t="17" w="4532" /><ent r="7" t="17" w="4548" /><ent r="7" t="17" w="4562" /><ent r="7" t="17" w="4576" /><ent r="7" t="17" w="4588" /><ent r="7" t="17" w="4601" /><ent r="7" t="17" w="4615" /><ent r="7" t="17" w="4629" /><ent r="7" t="17" w="4641" /><ent r="7" t="17" w="4709" /><ent r="7" t="17" w="4738" /><ent r="7" t="17" w="4750" /><ent r="7" t="17" w="4762" /><ent r="7" t="17" w="4776" /><ent r="7" t="17" w="4791" /><ent r="7" t="17" w="4807" /><ent r="7" t="17" w="4820" /><ent r="7" t="17" w="4834" /><ent r="7" t="17" w="5845" /><ent r="7" t="17" w="5845" /><ent r="7" t="17" w="5857" /><ent r="7" t="17" w="5870" /><ent r="7" t="17" w="5883" /><ent r="7" t="17" w="5896" /><ent r="7" t="17" w="5910" /><ent r="7" t="17" w="6257" /><ent r="7" t="17" w="6257" /><ent r="3" t="25" w="44" /><ent r="3" t="25" w="44" /><ent r="3" t="38" w="198" /><ent r="3" t="56" w="119" /><ent r="4" t="56" w="153" /><ent r="3" t="72" w="108" /><ent r="3" t="72" w="108" /></phr></stem><stem n="easy-to-us"><phr n="easy-to-use"><ent r="3" t="4" w="216" /><ent r="3" t="4" w="216" /></phr></stem><stem n="easi"><phr n="easy"><ent r="3" t="4" w="216" /></phr></stem><stem n="easy-to"><phr n="easy-to"><ent r="3" t="4" w="216" /></phr></stem><stem n="to-us"><phr n="to-use"><ent r="3" t="4" w="217" /></phr><phr n="to-user"><ent r="3" t="4" w="248" /></phr></stem><stem n="messag"><phr n="message"><ent r="3" t="4" w="220" /><ent r="3" t="4" w="220" /><ent r="3" t="48" w="462" /><ent r="3" t="48" w="462" /><ent r="3" t="48" w="468" /></phr><phr n="messages"><ent r="4" t="15" w="323" /><ent r="4" t="15" w="323" /><ent r="4" t="77" w="168" /><ent r="4" t="77" w="168" /><ent r="4" t="77" w="172" /><ent r="4" t="77" w="172" /><ent r="4" t="78" w="172" /><ent r="4" t="78" w="183" /><ent r="4" t="78" w="183" /><ent r="4" t="78" w="188" /><ent r="4" t="78" w="188" /></phr><phr n="Message"><ent r="7" t="17" w="5545" /><ent r="7" t="17" w="5545" /><ent r="7" t="17" w="5559" /><ent r="7" t="17" w="5559" /></phr><phr n="messaging"><ent r="6" t="79" w="353" /><ent r="6" t="79" w="353" /><ent r="6" t="79" w="501" /><ent r="6" t="79" w="501" /><ent r="6" t="79" w="1141" /><ent r="6" t="79" w="1141" /><ent r="6" t="79" w="1159" /></phr></stem><stem n="board"><phr n="boards"><ent r="3" t="4" w="221" /><ent r="3" t="4" w="221" /></phr></stem><stem n="opportun"><phr n="opportunity"><ent r="3" t="4" w="226" /><ent r="3" t="4" w="226" /><ent r="6" t="7" w="1085" /><ent r="6" t="7" w="1085" /><ent r="7" t="17" w="1624" /><ent r="7" t="17" w="1624" /><ent r="7" t="17" w="1638" /><ent r="7" t="17" w="1638" /><ent r="7" t="17" w="2282" /><ent r="7" t="17" w="2282" /><ent r="7" t="17" w="2296" /><ent r="7" t="17" w="2296" /><ent r="7" t="17" w="2943" /><ent r="7" t="17" w="2943" /><ent r="7" t="17" w="2957" /><ent r="7" t="17" w="2957" /><ent r="5" t="17" w="4847" /><ent r="5" t="17" w="4847" /><ent r="7" t="17" w="4858" /><ent r="7" t="17" w="4858" /><ent r="7" t="17" w="4870" /><ent r="7" t="17" w="4883" /><ent r="7" t="17" w="4896" /><ent r="7" t="17" w="4909" /><ent r="7" t="17" w="4922" /><ent r="7" t="17" w="4936" /><ent r="8" t="17" w="4950" /><ent r="8" t="17" w="4964" /><ent r="8" t="17" w="4979" /><ent r="8" t="17" w="4993" /><ent r="8" t="17" w="5020" /><ent r="8" t="17" w="5031" /><ent r="8" t="17" w="5042" /><ent r="8" t="17" w="5055" /><ent r="8" t="17" w="5071" /><ent r="8" t="17" w="5084" /><ent r="8" t="17" w="5097" /><ent r="8" t="17" w="5110" /><ent r="8" t="17" w="5123" /><ent r="7" t="17" w="5136" /><ent r="7" t="17" w="5150" /><ent r="7" t="17" w="5165" /><ent r="7" t="17" w="5177" /><ent r="7" t="17" w="5177" /><ent r="7" t="17" w="5189" /><ent r="7" t="17" w="5202" /><ent r="7" t="17" w="5215" /><ent r="7" t="17" w="5228" /><ent r="7" t="17" w="5241" /><ent r="7" t="17" w="6018" /><ent r="7" t="17" w="6018" /><ent r="7" t="17" w="6033" /><ent r="7" t="17" w="6047" /><ent r="7" t="17" w="6063" /><ent r="7" t="17" w="6078" /><ent r="7" t="17" w="6094" /><ent r="7" t="17" w="6109" /><ent r="7" t="17" w="6123" /><ent r="7" t="17" w="6136" /><ent r="7" t="17" w="6150" /><ent r="7" t="17" w="6282" /><ent r="7" t="17" w="6282" /><ent r="3" t="45" w="63" /><ent r="3" t="45" w="63" /><ent r="5" t="57" w="129" /></phr><phr n="opportunities"><ent r="6" t="7" w="937" /><ent r="6" t="7" w="937" /><ent r="6" t="7" w="1044" /><ent r="6" t="7" w="1052" /><ent r="6" t="7" w="1061" /><ent r="6" t="7" w="1069" /><ent r="6" t="7" w="1077" /><ent r="7" t="17" w="1496" /><ent r="7" t="17" w="1496" /><ent r="7" t="17" w="1508" /><ent r="7" t="17" w="1520" /><ent r="7" t="17" w="1533" /><ent r="7" t="17" w="1545" /><ent r="7" t="17" w="1559" /><ent r="7" t="17" w="1571" /><ent r="7" t="17" w="1584" /><ent r="7" t="17" w="1597" /><ent r="7" t="17" w="2156" /><ent r="7" t="17" w="2156" /><ent r="7" t="17" w="2168" /><ent r="7" t="17" w="2180" /><ent r="7" t="17" w="2193" /><ent r="7" t="17" w="2205" /><ent r="7" t="17" w="2218" /><ent r="7" t="17" w="2230" /><ent r="7" t="17" w="2243" /><ent r="7" t="17" w="2256" /><ent r="7" t="17" w="2817" /><ent r="7" t="17" w="2817" /><ent r="7" t="17" w="2829" /><ent r="7" t="17" w="2841" /><ent r="7" t="17" w="2854" /><ent r="7" t="17" w="2866" /><ent r="7" t="17" w="2879" /><ent r="7" t="17" w="2891" /><ent r="7" t="17" w="2904" /><ent r="7" t="17" w="2917" /><ent r="7" t="17" w="3004" /><ent r="7" t="17" w="3016" /><ent r="7" t="17" w="3029" /><ent r="7" t="17" w="3041" /><ent r="7" t="17" w="3054" /><ent r="7" t="17" w="3066" /><ent r="7" t="17" w="3079" /><ent r="7" t="17" w="3092" /><ent r="3" t="25" w="66" /><ent r="3" t="39" w="504" /><ent r="3" t="39" w="504" /><ent r="6" t="79" w="2021" /></phr><phr n="Opportunities"><ent r="6" t="7" w="1049" /><ent r="6" t="7" w="1066" /><ent r="6" t="7" w="1074" /><ent r="6" t="7" w="1082" /><ent r="6" t="7" w="1101" /><ent r="6" t="7" w="1112" /><ent r="6" t="7" w="1123" /><ent r="7" t="17" w="1499" /><ent r="7" t="17" w="1499" /><ent r="7" t="17" w="2159" /><ent r="7" t="17" w="2159" /><ent r="7" t="17" w="2820" /><ent r="7" t="17" w="2820" /><ent r="7" t="17" w="2995" /><ent r="7" t="17" w="2995" /><ent r="8" t="17" w="4849" /><ent r="8" t="17" w="4849" /><ent r="7" t="17" w="5168" /><ent r="7" t="17" w="5168" /><ent r="7" t="17" w="6082" /><ent r="7" t="17" w="6082" /><ent r="7" t="17" w="6098" /><ent r="7" t="17" w="6098" /><ent r="64" t="23" w="143" /><ent r="64" t="23" w="143" /><ent r="4" t="39" w="459" /><ent r="4" t="39" w="459" /><ent r="4" t="39" w="465" /><ent r="4" t="39" w="465" /><ent r="3" t="39" w="495" /><ent r="3" t="39" w="495" /><ent r="1000" t="44" w="1" /><ent r="1000" t="44" w="1" /><ent r="100" t="44" w="4" /><ent r="100" t="44" w="4" /><ent r="102" t="44" w="6" /><ent r="102" t="44" w="6" /><ent r="3" t="44" w="9" /><ent r="3" t="44" w="9" /><ent r="3" t="44" w="33" /><ent r="3" t="44" w="41" /><ent r="3" t="44" w="41" /><ent r="3" t="59" w="56" /></phr><phr n="Opportunity"><ent r="6" t="7" w="1050" /><ent r="6" t="7" w="1050" /><ent r="6" t="7" w="1067" /><ent r="6" t="7" w="1067" /><ent r="6" t="7" w="1075" /><ent r="6" t="7" w="1075" /><ent r="6" t="7" w="1083" /><ent r="6" t="7" w="1083" /><ent r="7" t="17" w="742" /><ent r="7" t="17" w="742" /><ent r="66" t="17" w="2973" /><ent r="66" t="17" w="2973" /><ent r="67" t="17" w="4838" /><ent r="67" t="17" w="4838" /><ent r="7" t="17" w="4861" /><ent r="7" t="17" w="4861" /><ent r="7" t="17" w="4875" /><ent r="7" t="17" w="4887" /><ent r="7" t="17" w="4887" /><ent r="7" t="17" w="4900" /><ent r="7" t="17" w="4900" /><ent r="7" t="17" w="4913" /><ent r="7" t="17" w="4913" /><ent r="7" t="17" w="4927" /><ent r="7" t="17" w="4927" /><ent r="8" t="17" w="5113" /><ent r="8" t="17" w="5113" /><ent r="7" t="17" w="5126" /><ent r="7" t="17" w="5126" /><ent r="7" t="17" w="5180" /><ent r="7" t="17" w="5180" /><ent r="7" t="17" w="5194" /><ent r="7" t="17" w="5206" /><ent r="7" t="17" w="5206" /><ent r="7" t="17" w="5219" /><ent r="7" t="17" w="5219" /><ent r="7" t="17" w="5232" /><ent r="7" t="17" w="5232" /><ent r="7" t="17" w="6008" /><ent r="7" t="17" w="6008" /><ent r="7" t="17" w="6113" /><ent r="7" t="17" w="6113" /><ent r="7" t="17" w="6126" /><ent r="7" t="17" w="6126" /><ent r="7" t="17" w="6140" /><ent r="7" t="17" w="6140" /><ent r="7" t="17" w="6272" /><ent r="7" t="17" w="6272" /><ent r="4" t="39" w="454" /><ent r="4" t="39" w="454" /><ent r="3" t="44" w="50" /><ent r="3" t="44" w="50" /><ent r="3" t="44" w="59" /><ent r="3" t="44" w="59" /><ent r="4" t="45" w="317" /><ent r="4" t="45" w="317" /><ent r="3" t="48" w="383" /><ent r="3" t="48" w="383" /><ent r="3" t="48" w="391" /><ent r="3" t="48" w="391" /><ent r="4" t="58" w="110" /><ent r="5" t="59" w="135" /><ent r="4" t="64" w="97" /><ent r="4" t="64" w="97" /></phr><phr n="Opportun"><ent r="7" t="17" w="730" /></phr></stem><stem n="talk"><phr n="talk"><ent r="3" t="4" w="228" /><ent r="3" t="4" w="228" /><ent r="4" t="41" w="82" /><ent r="4" t="41" w="82" /></phr></stem><stem n="brows"><phr n="browse"><ent r="3" t="4" w="235" /><ent r="3" t="4" w="235" /></phr><phr n="Browse"><ent r="65" t="14" w="201" /><ent r="65" t="14" w="201" /></phr></stem><stem n="post"><phr n="postings"><ent r="3" t="4" w="236" /></phr><phr n="post"><ent r="3" t="35" w="548" /><ent r="3" t="35" w="548" /></phr><phr n="posted"><ent r="3" t="45" w="279" /><ent r="3" t="45" w="279" /></phr></stem><stem n="ask"><phr n="ask"><ent r="3" t="4" w="237" /><ent r="3" t="4" w="237" /></phr></stem><stem n="question"><phr n="questions"><ent r="3" t="4" w="238" /></phr><phr n="question"><ent r="3" t="82" w="38" /><ent r="3" t="82" w="38" /><ent r="7" t="82" w="137" /><ent r="7" t="82" w="137" /></phr></stem><stem n="much"><phr n="much"><ent r="3" t="4" w="242" /><ent r="3" t="4" w="242" /></phr></stem><stem n="user-to-us"><phr n="user-to-user"><ent r="3" t="4" w="247" /><ent r="3" t="4" w="247" /></phr></stem><stem n="user-to"><phr n="user-to"><ent r="3" t="4" w="247" /></phr></stem><stem n="moder"><phr n="moderated"><ent r="3" t="4" w="254" /><ent r="3" t="4" w="254" /></phr></stem><stem n="analyst"><phr n="Analysts"><ent r="3" t="4" w="260" /></phr></stem><stem n="msdn"><phr n="msdn"><ent r="64" t="4" w="282" /></phr><phr n="MSDN"><ent r="3" t="4" w="287" /><ent r="3" t="4" w="287" /><ent r="3" t="45" w="241" /><ent r="3" t="45" w="241" /></phr></stem><stem n="librari"><phr n="Library"><ent r="3" t="4" w="288" /></phr><phr n="library"><ent r="3" t="24" w="101" /><ent r="3" t="24" w="101" /><ent r="4" t="62" w="54" /><ent r="4" t="62" w="54" /></phr></stem><stem n="effort"><phr n="effort"><ent r="3" t="4" w="298" /><ent r="3" t="4" w="298" /><ent r="3" t="72" w="219" /><ent r="3" t="72" w="219" /></phr></stem><stem n="accuraci"><phr n="accuracy"><ent r="3" t="4" w="305" /><ent r="3" t="4" w="305" /><ent r="3" t="72" w="226" /><ent r="3" t="72" w="226" /></phr></stem><stem n="swiftpag"><phr n="Swiftpage"><ent r="4" t="4" w="310" /><ent r="4" t="4" w="310" /><ent r="4" t="72" w="27" /><ent r="4" t="72" w="27" /><ent r="3" t="72" w="35" /><ent r="3" t="72" w="39" /><ent r="3" t="72" w="39" /><ent r="4" t="72" w="53" /><ent r="4" t="72" w="53" /><ent r="4" t="72" w="153" /><ent r="4" t="72" w="153" /><ent r="4" t="72" w="232" /><ent r="4" t="72" w="232" /><ent r="4" t="72" w="258" /><ent r="4" t="72" w="258" /></phr></stem><stem n="llc"><phr n="LLC"><ent r="4" t="4" w="312" /><ent r="4" t="4" w="312" /><ent r="4" t="72" w="29" /><ent r="4" t="72" w="29" /><ent r="4" t="72" w="55" /><ent r="4" t="72" w="55" /><ent r="4" t="72" w="155" /><ent r="4" t="72" w="155" /><ent r="4" t="72" w="234" /><ent r="4" t="72" w="234" /><ent r="4" t="72" w="260" /><ent r="4" t="72" w="260" /></phr></stem><stem n="reserv"><phr n="reserves"><ent r="3" t="4" w="314" /><ent r="3" t="4" w="314" /></phr><phr n="Reserved"><ent r="3" t="72" w="34" /></phr></stem><stem n="right"><phr n="right"><ent r="3" t="4" w="316" /><ent r="3" t="4" w="316" /></phr><phr n="Rights"><ent r="3" t="72" w="33" /><ent r="3" t="72" w="33" /></phr></stem><stem n="singl"><phr n="single"><ent r="3" t="4" w="320" /><ent r="3" t="4" w="320" /><ent r="3" t="49" w="47" /><ent r="3" t="49" w="47" /><ent r="6" t="75" w="92" /><ent r="6" t="75" w="92" /><ent r="7" t="82" w="61" /><ent r="7" t="82" w="61" /></phr><phr n="Single"><ent r="6" t="75" w="264" /><ent r="6" t="75" w="264" /></phr></stem><stem n="condit"><phr n="conditions"><ent r="3" t="4" w="327" /><ent r="3" t="4" w="327" /></phr><phr n="condition"><ent r="6" t="75" w="43" /></phr></stem><stem n="price"><phr n="pricing"><ent r="3" t="4" w="333" /><ent r="3" t="4" w="333" /></phr></stem><stem n="without"><phr n="without"><ent r="3" t="4" w="337" /><ent r="3" t="4" w="337" /><ent r="3" t="24" w="27" /><ent r="3" t="24" w="27" /><ent r="3" t="38" w="335" /><ent r="3" t="38" w="335" /><ent r="3" t="39" w="256" /><ent r="3" t="39" w="256" /><ent r="4" t="41" w="95" /><ent r="4" t="41" w="95" /><ent r="3" t="72" w="146" /><ent r="3" t="72" w="146" /><ent r="3" t="72" w="299" /><ent r="3" t="72" w="299" /><ent r="7" t="80" w="122" /><ent r="7" t="80" w="122" /></phr></stem><stem n="notic"><phr n="notice"><ent r="3" t="4" w="338" /><ent r="3" t="72" w="300" /></phr><phr n="Notice"><ent r="1000" t="72" w="4" /><ent r="1000" t="72" w="4" /><ent r="102" t="72" w="9" /><ent r="102" t="72" w="9" /></phr></stem><stem n="clearli"><phr n="clearly"><ent r="3" t="5" w="11" /><ent r="3" t="5" w="11" /></phr></stem><stem n="typograph"><phr n="Typographic"><ent r="4" t="5" w="19" /><ent r="4" t="5" w="19" /></phr></stem><stem n="standard"><phr n="Standard"><ent r="4" t="5" w="22" /><ent r="4" t="5" w="22" /><ent r="65" t="14" w="143" /><ent r="65" t="14" w="143" /><ent r="3" t="49" w="121" /><ent r="3" t="49" w="121" /></phr><phr n="standard"><ent r="3" t="14" w="258" /><ent r="3" t="14" w="258" /><ent r="3" t="35" w="71" /><ent r="3" t="35" w="71" /><ent r="3" t="45" w="240" /><ent r="3" t="45" w="240" /></phr></stem><stem n="paramet"><phr n="parameter"><ent r="4" t="5" w="26" /><ent r="4" t="5" w="26" /><ent r="6" t="5" w="178" /><ent r="6" t="5" w="178" /><ent r="6" t="5" w="183" /><ent r="6" t="5" w="183" /><ent r="3" t="27" w="229" /><ent r="3" t="27" w="229" /><ent r="3" t="27" w="286" /><ent r="3" t="27" w="286" /><ent r="3" t="27" w="356" /><ent r="3" t="27" w="356" /><ent r="3" t="28" w="247" /><ent r="3" t="28" w="247" /><ent r="3" t="33" w="40" /><ent r="3" t="33" w="40" /><ent r="4" t="52" w="81" /><ent r="4" t="52" w="100" /><ent r="4" t="55" w="94" /><ent r="4" t="61" w="174" /><ent r="4" t="61" w="174" /><ent r="4" t="63" w="136" /><ent r="4" t="63" w="136" /></phr><phr n="parameters"><ent r="6" t="5" w="154" /><ent r="6" t="5" w="154" /><ent r="3" t="65" w="441" /><ent r="3" t="65" w="441" /></phr><phr n="Parameters"><ent r="4" t="64" w="230" /><ent r="4" t="64" w="230" /><ent r="4" t="65" w="236" /><ent r="4" t="65" w="236" /></phr></stem><stem n="monospac"><phr n="Monospace"><ent r="6" t="5" w="35" /><ent r="6" t="5" w="35" /></phr></stem><stem n="input"><phr n="input"><ent r="6" t="5" w="42" /><ent r="6" t="5" w="42" /><ent r="6" t="5" w="124" /><ent r="6" t="5" w="176" /><ent r="6" t="79" w="4242" /><ent r="6" t="79" w="4242" /></phr></stem><stem n="line"><phr n="line"><ent r="6" t="5" w="46" /><ent r="6" t="5" w="127" /><ent r="6" t="5" w="175" /><ent r="4" t="67" w="121" /><ent r="4" t="67" w="121" /><ent r="4" t="67" w="140" /><ent r="4" t="67" w="140" /></phr><phr n="lines"><ent r="6" t="5" w="50" /><ent r="6" t="5" w="50" /></phr></stem><stem n="output"><phr n="output"><ent r="6" t="5" w="48" /><ent r="3" t="84" w="9" /><ent r="3" t="84" w="9" /><ent r="3" t="86" w="14" /></phr></stem><stem n="embed"><phr n="embedded"><ent r="6" t="5" w="51" /><ent r="6" t="5" w="51" /></phr></stem><stem n="variabl"><phr n="variables"><ent r="6" t="5" w="55" /><ent r="6" t="5" w="55" /></phr><phr n="Variables"><ent r="6" t="75" w="72" /><ent r="6" t="75" w="72" /></phr></stem><stem n="element"><phr n="elements"><ent r="6" t="5" w="58" /><ent r="6" t="5" w="69" /><ent r="6" t="5" w="111" /><ent r="3" t="22" w="34" /><ent r="3" t="22" w="34" /><ent r="4" t="37" w="472" /><ent r="3" t="86" w="9" /><ent r="3" t="86" w="9" /></phr></stem><stem n="public"><phr n="Public"><ent r="6" t="5" w="60" /><ent r="6" t="5" w="60" /><ent r="7" t="17" w="3713" /><ent r="7" t="17" w="3713" /><ent r="8" t="17" w="4020" /><ent r="8" t="17" w="4020" /><ent r="8" t="17" w="4233" /><ent r="8" t="17" w="4233" /><ent r="7" t="17" w="4403" /><ent r="7" t="17" w="4403" /><ent r="7" t="17" w="4674" /><ent r="7" t="17" w="4674" /><ent r="7" t="17" w="4928" /><ent r="7" t="17" w="4928" /></phr><phr n="public"><ent r="6" t="7" w="562" /><ent r="6" t="7" w="562" /><ent r="3" t="13" w="125" /><ent r="3" t="13" w="125" /><ent r="3" t="28" w="330" /><ent r="3" t="28" w="330" /><ent r="3" t="28" w="371" /><ent r="3" t="28" w="371" /><ent r="3" t="28" w="378" /><ent r="3" t="28" w="378" /><ent r="3" t="28" w="521" /><ent r="3" t="28" w="521" /><ent r="3" t="28" w="533" /><ent r="3" t="28" w="533" /><ent r="3" t="31" w="756" /><ent r="3" t="31" w="756" /><ent r="3" t="31" w="824" /><ent r="3" t="31" w="824" /><ent r="3" t="34" w="159" /><ent r="3" t="34" w="159" /><ent r="3" t="53" w="110" /><ent r="3" t="53" w="110" /><ent r="4" t="65" w="479" /><ent r="4" t="65" w="479" /></phr></stem></index>